blast2galaxy/__init__.py
blast2galaxy/api/__init__.py
blast2galaxy/api/blast_request.py
blast2galaxy/api/choices.py
blast2galaxy/api/help_texts.py
blast2galaxy/api/server_info.py
blast2galaxy/cli.py
blast2galaxy/config.py
blast2galaxy/errors.py
blast2galaxy/utils.py
blast2galaxy-1.0.0.dist-info/LICENSE
blast2galaxy-1.0.0.dist-info/METADATA
blast2galaxy-1.0.0.dist-info/WHEEL
blast2galaxy-1.0.0.dist-info/entry_points.txt
blast2galaxy-1.0.0.dist-info/RECORD
